likert/__init__.py
likert/examples/__init__.py
likert/examples/in_their_own_words/__init__.py
likert-0.0.2.dist-info/LICENSE
likert-0.0.2.dist-info/METADATA
likert-0.0.2.dist-info/WHEEL
likert-0.0.2.dist-info/top_level.txt
likert-0.0.2.dist-info/RECORD
